fast_vector_similarity-0.1.5.dist-info/METADATA
fast_vector_similarity-0.1.5.dist-info/WHEEL
fast_vector_similarity/__init__.py
fast_vector_similarity/fast_vector_similarity.cpython-310-x86_64-linux-gnu.so
fast_vector_similarity-0.1.5.dist-info/RECORD
