Metadata-Version: 2.3
Name: fast_vector_similarity
Version: 0.1.5
Classifier: Development Status :: 3 - Alpha
Classifier: Intended Audience :: Developers
Classifier: License :: OSI Approved :: MIT License
Classifier: Programming Language :: Rust
Classifier: Programming Language :: Python :: 3
Classifier: Programming Language :: Python :: 3.9
Classifier: Programming Language :: Python :: 3.10
Classifier: Programming Language :: Python :: 3.11
Classifier: Programming Language :: Python :: 3.12
Summary: Compute various vector similarity metrics in Rust for Python, including bootstrapped/bagged robust estimators.
Author-email: Jeffrey Emanuel <jeff@pastel.network>
License: MIT
